stripe_api_client/__init__.py
stripe_api_client/client.py
stripe_api_client/resources/__init__.py
stripe_api_client/resources/base.py
stripe_api_client/resources/charges.py
stripe_api_client/resources/customers.py
stripe_api_client/resources/invoices.py
stripe_api_client/resources/payment_intents.py
stripe_api_client/resources/payment_methods.py
stripe_api_client/resources/subscriptions.py
stripe_api_client/utils.py
stripe_api_client-0.1.3.dist-info/WHEEL
stripe_api_client-0.1.3.dist-info/METADATA
stripe_api_client-0.1.3.dist-info/RECORD
