Metadata-Version: 2.1
Name: stripe-api-client
Version: 0.1.3
Summary: 
Author: Steven Athouel
Author-email: sathouel@gmail.com
Requires-Python: >=3.9,<4.0
Classifier: Programming Language :: Python :: 3
Classifier: Programming Language :: Python :: 3.9
Classifier: Programming Language :: Python :: 3.10
Classifier: Programming Language :: Python :: 3.11
Requires-Dist: requests (>=2.31.0,<3.0.0)
